dsplus/__init__.py
dsplus/pb_functions_general.py
dsplus/pb_functions_pandas.py
dsplus/pb_functions_plotly.py
dsplus/pb_functions_spatial.py
dsplus-0.9.6.dist-info/licenses/LICENSE
dsplus-0.9.6.dist-info/METADATA
dsplus-0.9.6.dist-info/WHEEL
dsplus-0.9.6.dist-info/top_level.txt
dsplus-0.9.6.dist-info/RECORD
