Metadata-Version: 2.4
Name: dsplus
Version: 0.9.6
Summary: Helper functions for data science applications
Author: Prashana Bajracharya
Author-email: pajracharya713@gmail.com
Keywords: data science,pandas,geopandas
Classifier: Programming Language :: Python :: 3
Classifier: Programming Language :: Python :: 3.10
Classifier: Programming Language :: Python :: 3.11
Classifier: Programming Language :: Python :: 3.12
Classifier: Programming Language :: Python :: 3.13
Classifier: License :: OSI Approved :: MIT License
Classifier: Development Status :: 4 - Beta
Requires-Python: >=3.10
License-File: LICENSE
Requires-Dist: numpy
Requires-Dist: pandas
Requires-Dist: statsmodels
Requires-Dist: scipy
Requires-Dist: plotly
Requires-Dist: geopandas
Requires-Dist: shapely
Requires-Dist: rasterio
Requires-Dist: rioxarray
Requires-Dist: rasterstats
Requires-Dist: xarray
Dynamic: author
Dynamic: author-email
Dynamic: classifier
Dynamic: description
Dynamic: description-content-type
Dynamic: keywords
Dynamic: license-file
Dynamic: requires-dist
Dynamic: requires-python
Dynamic: summary
